ms2vec/__init__.py
ms2vec/bge_model.py
ms2vec/cosent_model.py
ms2vec/ngram.py
ms2vec/sentence_model.py
ms2vec/similarity.py
ms2vec/stopwords.txt
ms2vec/word2vec.py
ms2vec/utils/__init__.py
ms2vec/utils/distance.py
ms2vec/utils/stats_util.py
ms2vec/utils/tokenizer.py
ms2vec-0.0.2.dist-info/LICENSE
ms2vec-0.0.2.dist-info/METADATA
ms2vec-0.0.2.dist-info/WHEEL
ms2vec-0.0.2.dist-info/top_level.txt
ms2vec-0.0.2.dist-info/RECORD
