Metadata-Version: 2.1
Name: ms2vec
Version: 0.0.2
Summary: MindSpore Text to vector Tool, encode text
Home-page: https://github.com/lvyufeng/ms2vec
Author: Lvyufeng
Author-email: lvyufeng@cqu.edu.cn
License: Apache License 2.0
Keywords: word embedding,text2vec,Chinese Text Similarity Calculation Tool,similarity,word2vec
Classifier: Development Status :: 5 - Production/Stable
Classifier: Intended Audience :: Developers
Classifier: Intended Audience :: Education
Classifier: Intended Audience :: Science/Research
Classifier: License :: OSI Approved :: Apache Software License
Classifier: Operating System :: OS Independent
Classifier: Programming Language :: Python :: 3
Classifier: Topic :: Scientific/Engineering :: Artificial Intelligence
Requires-Python: >=3.7.0
License-File: LICENSE
Requires-Dist: jieba
Requires-Dist: mindnlp
Requires-Dist: tqdm
Requires-Dist: scikit-learn
Requires-Dist: pandas
